ginear/__init__.py
ginear/__main__.py
ginear/ginear.py
ginear/queries.py
ginear/utils.py
ginear-0.1.24.dist-info/METADATA
ginear-0.1.24.dist-info/WHEEL
ginear-0.1.24.dist-info/entry_points.txt
ginear-0.1.24.dist-info/RECORD
